setup.py
tornaqiniu/__init__.py
tornaqiniu/auth.py
tornaqiniu/compat.py
tornaqiniu/config.py
tornaqiniu/http.py
tornaqiniu/main.py
tornaqiniu/tornadohttpclient.py
tornaqiniu/utils.py
tornaqiniu.egg-info/PKG-INFO
tornaqiniu.egg-info/SOURCES.txt
tornaqiniu.egg-info/dependency_links.txt
tornaqiniu.egg-info/entry_points.txt
tornaqiniu.egg-info/requires.txt
tornaqiniu.egg-info/top_level.txt
tornaqiniu/services/__init__.py
tornaqiniu/services/processing/__init__.py
tornaqiniu/services/processing/cmd.py
tornaqiniu/services/processing/pfop.py
tornaqiniu/services/storage/__init__.py
tornaqiniu/services/storage/bucket.py
tornaqiniu/services/storage/uploader.py